sqlmodel_basecrud/__init__.py
sqlmodel_basecrud/basecrud.py
sqlmodel_basecrud/baserepository.py
sqlmodel_basecrud-0.1.9.dist-info/LICENSE
sqlmodel_basecrud-0.1.9.dist-info/WHEEL
sqlmodel_basecrud-0.1.9.dist-info/METADATA
sqlmodel_basecrud-0.1.9.dist-info/RECORD
