Metadata-Version: 2.1
Name: sqlmodel-basecrud
Version: 0.1.9
Summary: Simple package that provides base CRUD operations for your models.
Home-page: https://github.com/woofz/sqlmodel-basecrud
License: MIT
Keywords: sqlmodel,crud,fastapi,basecrud,fastapi-crud,fastapi-sqlmodel,sqlmodel,fastapi-sqlmodel-crud
Author: Danilo Aliberti
Author-email: danilo@woofz.dev
Requires-Python: >=3.7,<4.0
Classifier: Environment :: Web Environment
Classifier: Framework :: FastAPI
Classifier: License :: OSI Approved :: MIT License
Classifier: Programming Language :: Python :: 3
Classifier: Programming Language :: Python :: 3.10
Classifier: Programming Language :: Python :: 3.7
Classifier: Programming Language :: Python :: 3.8
Classifier: Programming Language :: Python :: 3.9
Classifier: Topic :: Database
Requires-Dist: SQLAlchemy (==1.4.35)
Requires-Dist: importlib-metadata (>=4.11.4,<5.0.0)
Requires-Dist: sqlmodel (>=0.0.6,<0.0.7)
Project-URL: Documentation, https://woofz.github.io/sqlmodel-basecrud/latest
Project-URL: Repository, https://github.com/woofz/sqlmodel-basecrud
